clickify/__init__.py
clickify/admin.py
clickify/apps.py
clickify/decorators.py
clickify/drf_exceptions.py
clickify/drf_urls.py
clickify/drf_views.py
clickify/exceptions.py
clickify/middleware.py
clickify/migrations/0001_initial.py
clickify/migrations/0002_clicklog_ref_alter_trackedlink_target_url.py
clickify/migrations/__init__.py
clickify/models.py
clickify/templatetags/__init__.py
clickify/templatetags/clickify_tags.py
clickify/urls.py
clickify/utils.py
clickify/views.py
django_clickify-0.3.0.dist-info/LICENSE
django_clickify-0.3.0.dist-info/METADATA
django_clickify-0.3.0.dist-info/WHEEL
django_clickify-0.3.0.dist-info/RECORD
