Metadata-Version: 2.3
Name: django-clickify
Version: 0.3.0
Summary: A Django app to track link clicks with rate limiting, IP filtering, and geolocation.
License: MIT
Keywords: django,click,tracker,ratelimit,ipfilter,geolocation,analytics
Author: Md Romjan Ali
Author-email: romjanvr5@gmail.com
Requires-Python: >=3.10
Classifier: Development Status :: 4 - Beta
Classifier: Environment :: Web Environment
Classifier: Framework :: Django
Classifier: Framework :: Django :: 4.2
Classifier: Framework :: Django :: 5.0
Classifier: Intended Audience :: Developers
Classifier: License :: OSI Approved :: MIT License
Classifier: Operating System :: OS Independent
Classifier: Programming Language :: Python
Classifier: Programming Language :: Python :: 3
Classifier: Programming Language :: Python :: 3.10
Classifier: Programming Language :: Python :: 3.11
Classifier: Programming Language :: Python :: 3.12
Classifier: Programming Language :: Python :: 3.13
Classifier: Topic :: Internet :: WWW/HTTP
Classifier: Topic :: Internet :: WWW/HTTP :: Dynamic Content
Classifier: Topic :: Software Development :: Libraries :: Application Frameworks
Classifier: Topic :: Software Development :: Libraries :: Python Modules
Provides-Extra: drf
Provides-Extra: full
Provides-Extra: ratelimit
Requires-Dist: django (>=4.2,<6)
Project-URL: Documentation, https://github.com/romjanxr/django-clickify#readme
Project-URL: Homepage, https://github.com/romjanxr/django-clickify
Project-URL: Repository, https://github.com/romjanxr/django-clickify
